Metadata-Version: 1.0
Name: TS-distributions
Version: 1.1
Summary: Gaussian & Binomial distributions
Home-page: UNKNOWN
Author: Tarun Saxena
Author-email: tarunsaxena16@gmail.com
License: UNKNOWN
Platform: UNKNOWN
